stock_data_server/__init__.py
stock_data_server/__main__.py
stock_data_server/client_secrets.json
stock_data_server/credentials.json
stock_data_server/stock_data_server.py
stock_data_server-0.1.0.dist-info/METADATA
stock_data_server-0.1.0.dist-info/WHEEL
stock_data_server-0.1.0.dist-info/entry_points.txt
stock_data_server-0.1.0.dist-info/RECORD
