Metadata-Version: 2.4
Name: stock-data-server
Version: 0.1.0
Summary: Add your description here
Author-email: Ashutoshsahu-13 <ashutoshsahu243@gmail.com>
Requires-Python: >=3.13
Requires-Dist: build>=1.2.2.post1
Requires-Dist: dotenv>=0.9.9
Requires-Dist: fastmcp>=2.10.4
Requires-Dist: langchain-core>=0.3.68
Requires-Dist: langchain-experimental>=0.3.4
Requires-Dist: langchain-groq>=0.3.5
Requires-Dist: langchain>=0.3.26
Requires-Dist: matplotlib>=3.10.3
Requires-Dist: mcp[cil,cli]>=1.11.0
Requires-Dist: openpyxl>=3.1.5
Requires-Dist: pandas>=2.3.1
Requires-Dist: pydrive>=1.3.1
Requires-Dist: seaborn>=0.13.2
Requires-Dist: twine>=6.1.0
